moovai/__init__.py
moovai/test.py
moovai/data/__init__.py
moovai/data/model_building.py
moovai/data/postprocess.py
moovai/data/preprocess.py
moovai/google_cloud/__init__.py
moovai/google_cloud/bigquery.py
moovai/google_cloud/cloud_storage.py
moovai/model/__init__.py
moovai/model/create_model_ai_platform.py
moovai/model/get_prediction.py
moovai/model/keras_to_savedmodel.py
moovai-0.0.9.data/scripts/bigquery.py
moovai-0.0.9.data/scripts/cloud_storage.py
moovai-0.0.9.data/scripts/create_model_ai_platform.py
moovai-0.0.9.data/scripts/get_prediction.py
moovai-0.0.9.data/scripts/keras_to_savedmodel.py
moovai-0.0.9.data/scripts/model_building.py
moovai-0.0.9.data/scripts/postprocess.py
moovai-0.0.9.data/scripts/preprocess.py
moovai-0.0.9.data/scripts/test.py
moovai-0.0.9.dist-info/LICENSE
moovai-0.0.9.dist-info/METADATA
moovai-0.0.9.dist-info/WHEEL
moovai-0.0.9.dist-info/top_level.txt
moovai-0.0.9.dist-info/RECORD
