Metadata-Version: 2.1
Name: moovai
Version: 0.0.9
Summary: A package for working with GCS and BigQuery
Home-page: https://github.com/moovai/Toolbox/
Author: Antsa Randriamihaja
Author-email: antsa.randriamihaja@moov.ai
License: UNKNOWN
Project-URL: Documentation, https://github.com/moovai/Toolbox/blob/master/README.md
Project-URL: Source Code, https://github.com/moovai/Toolbox/tree/master/MoovAI
Platform: UNKNOWN
Classifier: Programming Language :: Python :: 3.6
Classifier: License :: OSI Approved :: MIT License
Classifier: Operating System :: OS Independent
Requires-Dist: google-cloud-error-reporting (==0.31.0)
Requires-Dist: google-cloud-bigquery (==1.15.0)
Requires-Dist: google-cloud-storage (==1.16.1)
Requires-Dist: joblib
Requires-Dist: pandas
Requires-Dist: scikit-learn
Requires-Dist: pysnooper
Requires-Dist: tensorflow
Requires-Dist: keras
Requires-Dist: matplotlib
